{
  "fill" : {
    "linear-gradient" : [
      "display-p3:0.36471,0.69412,1.00000,1.00000",
      "display-p3:0.00000,0.51765,1.00000,1.00000"
    ],
    "orientation" : {
      "start" : {
        "x" : 0.5,
        "y" : 0
      },
      "stop" : {
        "x" : 0.5,
        "y" : 0.7
      }
    }
  },
  "groups" : [
    {
      "layers" : [
        {
          "image-name" : "Vector.png",
          "name" : "Vector",
          "position" : {
            "scale" : 0.46,
            "translation-in-points" : [
              0,
              0
            ]
          }
        },
        {
          "blend-mode" : "normal",
          "glass" : false,
          "hidden" : false,
          "image-name" : "flakes.png",
          "name" : "flakes",
          "position" : {
            "scale" : 0.6,
            "translation-in-points" : [
              0,
              0
            ]
          }
        }
      ],
      "shadow" : {
        "kind" : "neutral",
        "opacity" : 0.5
      },
      "translucency" : {
        "enabled" : true,
        "value" : 0.5
      }
    }
  ],
  "supported-platforms" : {
    "circles" : [
      "watchOS"
    ],
    "squares" : "shared"
  }
}